dp_file_system_file/__init__.py
dp_file_system_file/apps.py
dp_file_system_file/models.py
dp_file_system_file/tests.py
dp_file_system_file/migrations/0001_initial.py
dp_file_system_file/migrations/__init__.py
dp_file_system_file-0.0.2.dist-info/LICENSE
dp_file_system_file-0.0.2.dist-info/METADATA
dp_file_system_file-0.0.2.dist-info/WHEEL
dp_file_system_file-0.0.2.dist-info/top_level.txt
dp_file_system_file-0.0.2.dist-info/RECORD
