Metadata-Version: 2.1
Name: dp-file-system-file
Version: 0.0.2
Summary: Represent files on the file system
Home-page: UNKNOWN
Author: Kai Hoppert
Author-email: kai.hoppert@gmail.com
License: UNKNOWN
Platform: UNKNOWN
Classifier: Development Status :: 5 - Production/Stable
Classifier: Intended Audience :: Developers
Classifier: Topic :: Software Development :: Build Tools
Classifier: License :: OSI Approved :: MIT License
Classifier: Programming Language :: Python :: 3
Classifier: Framework :: Django :: 2.0
Classifier: Framework :: Django :: 2.1
Classifier: Framework :: Django :: 2.2
Requires-Dist: Django
